cups_printers/__init__.py
cups_printers/commands/__init__.py
cups_printers/commands/output.py
cups_printers/commands/queue.py
cups_printers/commands/state.py
cups_printers/constants.py
cups_printers/main.py
cups_printers/maiqqqqqqn.py
cups_printers-1.0.0.dist-info/LICENSE
cups_printers-1.0.0.dist-info/METADATA
cups_printers-1.0.0.dist-info/WHEEL
cups_printers-1.0.0.dist-info/entry_points.txt
cups_printers-1.0.0.dist-info/RECORD
