Metadata-Version: 2.1
Name: cups-printers
Version: 1.0.0
Summary: Tool to get the printers from a running CUPS instance
Home-page: https://github.com/audiusGmbH/cups-printers
License: MIT
Keywords: printers,cups
Author: Fabian Affolter
Author-email: fabian.affolter@audius.de
Requires-Python: >=3.11,<4.0
Classifier: License :: OSI Approved :: MIT License
Classifier: Programming Language :: Python :: 3
Classifier: Programming Language :: Python :: 3.11
Classifier: Programming Language :: Python :: 3.12
Requires-Dist: pycups (>=2.0.1,<3.0.0)
Requires-Dist: typer[all] (>=0.9.0,<0.10.0)
Requires-Dist: validators (>=0.23.2,<0.24.0)
Project-URL: Repository, https://github.com/audiusGmbH/cups-printers
